rainod/__init__.py
rainod/rb.py
rainod-1.0.8.dist-info/METADATA
rainod-1.0.8.dist-info/WHEEL
rainod-1.0.8.dist-info/top_level.txt
rainod-1.0.8.dist-info/RECORD
