Metadata-Version: 2.1
Name: rainod
Version: 1.0.8
Summary: 2조 패키지
Home-page: UNKNOWN
Author: dojun
Author-email: ehwns4337@naver.com
License: MIT
Platform: UNKNOWN
Requires-Python: >=3
